odoo/addons/endpoint_auth_api_key/README.rst
odoo/addons/endpoint_auth_api_key/__init__.py
odoo/addons/endpoint_auth_api_key/__manifest__.py
odoo/addons/endpoint_auth_api_key/demo/api_key_demo.xml
odoo/addons/endpoint_auth_api_key/demo/endpoint_demo.xml
odoo/addons/endpoint_auth_api_key/i18n/endpoint_auth_api_key.pot
odoo/addons/endpoint_auth_api_key/i18n/it.po
odoo/addons/endpoint_auth_api_key/models/__init__.py
odoo/addons/endpoint_auth_api_key/models/endpoint_mixin.py
odoo/addons/endpoint_auth_api_key/readme/CONTRIBUTORS.rst
odoo/addons/endpoint_auth_api_key/readme/DESCRIPTION.rst
odoo/addons/endpoint_auth_api_key/static/description/icon.png
odoo/addons/endpoint_auth_api_key/static/description/index.html
odoo/addons/endpoint_auth_api_key/tests/__init__.py
odoo/addons/endpoint_auth_api_key/tests/test_endpoint.py
odoo/addons/endpoint_auth_api_key/tests/test_endpoint_controller.py
odoo/addons/endpoint_auth_api_key/views/endpoint_view.xml
odoo14_addon_endpoint_auth_api_key-14.0.1.2.1.dist-info/METADATA
odoo14_addon_endpoint_auth_api_key-14.0.1.2.1.dist-info/WHEEL
odoo14_addon_endpoint_auth_api_key-14.0.1.2.1.dist-info/top_level.txt
odoo14_addon_endpoint_auth_api_key-14.0.1.2.1.dist-info/RECORD
